binaryflow/__init__.py
binaryflow/client.py
binaryflow/server.py
binaryflow-1.1.1.dist-info/LICENSE
binaryflow-1.1.1.dist-info/METADATA
binaryflow-1.1.1.dist-info/WHEEL
binaryflow-1.1.1.dist-info/top_level.txt
binaryflow-1.1.1.dist-info/RECORD
