Metadata-Version: 2.1
Name: binaryflow
Version: 1.1.1
Summary: A custom file transmission utility based on the Binary Flow Protocol for transferring files using IP and hostname.
Home-page: https://github.com/krishnagopaljha/binaryflow
Author: Krishna Gopal Jha
Classifier: Programming Language :: Python :: 3
Classifier: License :: OSI Approved :: Apache Software License
Classifier: Operating System :: OS Independent
Requires-Python: >=3.6
License-File: LICENSE
